tr/__init__.py
tr/char_table.txt
tr/conlib.py
tr/crnn.bin
tr/gui.py
tr/libtr.dll
tr-2.8.6.dist-info/METADATA
tr-2.8.6.dist-info/WHEEL
tr-2.8.6.dist-info/top_level.txt
tr-2.8.6.dist-info/RECORD
